ppwebdataset/__init__.py
ppwebdataset/autodecode.py
ppwebdataset/bench.py
ppwebdataset/cache.py
ppwebdataset/cborsiterators.py
ppwebdataset/compat.py
ppwebdataset/downloader.py
ppwebdataset/extradatasets.py
ppwebdataset/filters.py
ppwebdataset/gopen.py
ppwebdataset/handlers.py
ppwebdataset/mix.py
ppwebdataset/multi.py
ppwebdataset/paddle.py
ppwebdataset/pipeline.py
ppwebdataset/pytorch.py
ppwebdataset/shardlists.py
ppwebdataset/tariterators.py
ppwebdataset/tenbin.py
ppwebdataset/typecheck.py
ppwebdataset/utils.py
ppwebdataset/writer.py
ppwids/__init__.py
ppwids/wids.py
ppwids/wids_bench.py
ppwids/wids_cleanup.py
ppwids/wids_dir.py
ppwids/wids_dl.py
ppwids/wids_index.py
ppwids/wids_lru.py
ppwids/wids_mmtar.py
ppwids/wids_specs.py
ppwids/wids_tar.py
ppwebdataset-0.2.86.dist-info/LICENSE
ppwebdataset-0.2.86.dist-info/METADATA
ppwebdataset-0.2.86.dist-info/WHEEL
ppwebdataset-0.2.86.dist-info/entry_points.txt
ppwebdataset-0.2.86.dist-info/top_level.txt
ppwebdataset-0.2.86.dist-info/RECORD
