Metadata-Version: 2.1
Name: ppwebdataset
Version: 0.2.86
Summary: Record sequential storage for deep learning.
Home-page: http://github.com/JunnYu/ppwebdataset
Author: JunnYu
Author-email: 573009727@qq.com
License: MIT
Keywords: object store,client,deep learning
Classifier: Development Status :: 3 - Alpha
Classifier: License :: OSI Approved :: BSD License
Classifier: Programming Language :: Python :: 3.6
Classifier: Programming Language :: Python :: 3.7
Classifier: Programming Language :: Python :: 3.8
Classifier: Programming Language :: Python :: 3.9
Requires-Python: >=3.6
License-File: LICENSE
Requires-Dist: braceexpand
Requires-Dist: numpy
Requires-Dist: pyyaml
